lesscode_charts/__init__.py
lesscode_charts/version.py
lesscode_charts/v1/__init__.py
lesscode_charts/v1/forest_chart.py
lesscode_charts/v1/heat_map_chart.py
lesscode_charts/v1/histogram_chart.py
lesscode_charts/v1/k_line_chart.py
lesscode_charts/v1/layout_chart.py
lesscode_charts/v1/list_chart.py
lesscode_charts/v1/pie_chart.py
lesscode_charts/v1/pyramid_chart.py
lesscode_charts/v1/radar_chart.py
lesscode_charts/v1/rect_chart.py
lesscode_charts/v1/relation_chart.py
lesscode_charts/v1/sankey_chart.py
lesscode_charts/v1/scatter_chart.py
lesscode_charts/v1/table_chart.py
lesscode_charts/v1/univalent_graph_chart.py
lesscode_charts/v1/word_cloud_chart.py
lesscode_charts/v2/__init__.py
lesscode_charts/v2/forest_chart.py
lesscode_charts/v2/heat_map_chart.py
lesscode_charts/v2/histogram_chart.py
lesscode_charts/v2/k_line_chart.py
lesscode_charts/v2/pie_chart.py
lesscode_charts/v2/pyramid_chart.py
lesscode_charts/v2/radar_chart.py
lesscode_charts/v2/relation_chart.py
lesscode_charts/v2/sankey_chart.py
lesscode_charts/v2/scatter_chart.py
lesscode_charts/v2/table_chart.py
lesscode_charts/v2/univalent_graph_chart.py
lesscode_charts/v2/word_cloud_chart.py
lesscode_charts-0.1.0.dist-info/METADATA
lesscode_charts-0.1.0.dist-info/WHEEL
lesscode_charts-0.1.0.dist-info/top_level.txt
lesscode_charts-0.1.0.dist-info/RECORD
