Metadata-Version: 2.1
Name: lesscode-charts
Version: 0.1.0
Summary: Add your description here
Author: Chao.yy
Author-email: yuyc@ishangqi.com
Platform: python
Classifier: Programming Language :: Python :: 3
Classifier: Operating System :: OS Independent
Requires-Python: >=3.6
Requires-Dist: setuptools >=75.3.2
Requires-Dist: twine >=6.1.0
Requires-Dist: wheel >=0.45.1
